{
    "checked": false,
    "name": "Optimus Prime™",
    "number": "ICX204",
    "difficulty": 7,
    "sheets": 3,
    "link": "https://www.metalearth.com/transformers/iconx-optimus-prime",
    "category": "Transformers™",
    "type": "ICONX",
    "status": "",
    "instructionsLink": "https://www.metalearth.com/download/sample/359",
    "360View": "https://www.metalearth.com/360/ICX204",
    "description": "",
    "productimage": "https://www.metalearth.com/content/images/thumbs/0005047_premium-series-optimus-prime_570.png"
}