{
    "checked": false,
    "name": "Imperial AT-Hauler™",
    "number": "MMS410",
    "difficulty": null,
    "sheets": 2,
    "link": "https://www.metalearth.com/starwars/imperial-at-hauler",
    "category": "Star Wars™",
    "type": "Metal Earth",
    "status": "Retired",
    "instructionsLink": "https://www.metalearth.com/download/sample/313",
    "360View": "https://www.metalearth.com/360/MMS410",
    "description": "",
    "productimage": "https://www.metalearth.com/content/images/thumbs/0002389_imperial-at-haulertrade_570.png"
}